require_i18n/__init__.py
require_i18n/core.py
require_i18n/util.py
require_i18n/management/__init__.py
require_i18n/management/commands/__init__.py
require_i18n/management/commands/compile_js.py
django_require_i18n-1.3.0.dist-info/LICENSE
django_require_i18n-1.3.0.dist-info/METADATA
django_require_i18n-1.3.0.dist-info/WHEEL
django_require_i18n-1.3.0.dist-info/top_level.txt
django_require_i18n-1.3.0.dist-info/RECORD
